[
    {
        "offer": {
            "offer": "FoodBand.ru",
            "website": "https://foodband.ru/",
            "cashback": 10,
            "period": 0,
            "offer_type": 0,
            "advert_text": "Foodband.ru - это круглосуточная доставка пиццы, вок и суши в Москве. Для самых голодных в меню представлено более 25 видов пицц, 35 видов роллов и суши, а также сочные воки, пикантные соусы и ещё много всего вкусного. Скидка предоставляется при оплате на сайте."
        },
        "product": [
            {
                "Item": "десерт~Торт \"Тирамису\"",
                "Attributes": "Шоколадно-кофейный бисквит, крем на основе сыра и сливок, какао-пудра",
                "Price": 275
            }
        ]
    },
    {
        "offer": {
            "offer": "Абрикос",
            "website": "https://www.abri-kos.ru/",
            "cashback": 5,
            "period": 0,
            "offer_type": 0,
            "advert_text": "Компания Абрикос - это Интернет магазин продуктов питания: огромный ассортимент свежих и замороженных продуктов, бакалеи и бытовой химии. Доставка в удобное для вас время. Самовывоз ежедневно с 10.00 до 18.00. Продукция сертифицирована и зарегистрирована в системе Меркурий. Приятных покупок и хорошего настроения! Спецпредложение действует при условии оплаты на сайте компании или курьеру."
        },
        "product": [
            {
                "Item": "Хлебобулочные и кондитерские изделия~Торты и пирожные~Пироги~Пирог Постный с цукатами и изюмом 500г",
                "Attributes": "Пирог Постный с цукатами и изюмом, 500 г.Состав Мука пшеничная в/с, сахар, масло растительное, вода, цукаты, изюм, разрыхлитель, сахарная пудра, соль. Условия и сроки хранения при темп. от +2 о C до +6 о С, 30 сут.",
                "Price": 125
            }
        ]
    },
    {
        "offer": {
            "offer": "Абрикос",
            "website": "https://www.abri-kos.ru/",
            "cashback": 5,
            "period": 0,
            "offer_type": 0,
            "advert_text": "Компания Абрикос - это Интернет магазин продуктов питания: огромный ассортимент свежих и замороженных продуктов, бакалеи и бытовой химии. Доставка в удобное для вас время. Самовывоз ежедневно с 10.00 до 18.00. Продукция сертифицирована и зарегистрирована в системе Меркурий. Приятных покупок и хорошего настроения! Спецпредложение действует при условии оплаты на сайте компании или курьеру."
        },
        "product": [
            {
                "Item": "Хлебобулочные и кондитерские изделия~Торты и пирожные~Пироги~Пирог Постный с курагой и изюмом 500г",
                "Attributes": "Пирог Постный с курагой и изюмом, 500 г.Состав Мука пшеничная в/с, сахар, масло растительное, вода, изюм, курага, разрыхлитель, сахарная пудра, соль. Условия и сроки хранения при темп. от +2 о C до +6 о С, 30 сут.",
                "Price": 129
            }
        ]
    },
    {
        "offer": {
            "offer": "Абрикос",
            "website": "https://www.abri-kos.ru/",
            "cashback": 5,
            "period": 0,
            "offer_type": 0,
            "advert_text": "Компания Абрикос - это Интернет магазин продуктов питания: огромный ассортимент свежих и замороженных продуктов, бакалеи и бытовой химии. Доставка в удобное для вас время. Самовывоз ежедневно с 10.00 до 18.00. Продукция сертифицирована и зарегистрирована в системе Меркурий. Приятных покупок и хорошего настроения! Спецпредложение действует при условии оплаты на сайте компании или курьеру."
        },
        "product": [
            {
                "Item": "Хлебобулочные и кондитерские изделия~Торты и пирожные~Пироги~Пирог Постный с черносливом и изюмом 500г",
                "Attributes": "Пирог Постный с черносливом и изюмом, 500 г.Состав Мука пшеничная в/с, сахар, масло растительное, вода, изюм, чернослив сушеный резаный, разрыхлитель, сахарная пудра, соль. Условия и сроки хранения при темп. от +2 о C до +6 о С, 30 сут.",
                "Price": 125
            }
        ]
    },
    {
        "offer": {
            "offer": "Абрикос",
            "website": "https://www.abri-kos.ru/",
            "cashback": 5,
            "period": 0,
            "offer_type": 0,
            "advert_text": "Компания Абрикос - это Интернет магазин продуктов питания: огромный ассортимент свежих и замороженных продуктов, бакалеи и бытовой химии. Доставка в удобное для вас время. Самовывоз ежедневно с 10.00 до 18.00. Продукция сертифицирована и зарегистрирована в системе Меркурий. Приятных покупок и хорошего настроения! Спецпредложение действует при условии оплаты на сайте компании или курьеру."
        },
        "product": [
            {
                "Item": "Хлебобулочные и кондитерские изделия~Торты и пирожные~Пироги~Пирог Постный с морковью и изюмом 500г",
                "Attributes": "Пирог Постный с морковью и изюмом, 500 г.Состав Мука пшеничная в/с, сахар, масло растительное, вода, изюм, морковь сушеная, сахарная пудра, разрыхлитель, соль. Условия и сроки хранения при темп. от +2 о C до +6 о С, 30 сут.",
                "Price": 116
            }
        ]
    }
]